biodata/__init__.py
biodata/baseio.py
biodata/bed.py
biodata/bigwig.py
biodata/delimited.py
biodata/fasta.py
biodata/gff.py
biodata/meme.py
biodata/tabix.py
biodata-0.1.5.dist-info/METADATA
biodata-0.1.5.dist-info/WHEEL
biodata-0.1.5.dist-info/top_level.txt
biodata-0.1.5.dist-info/RECORD
