Metadata-Version: 2.1
Name: biodata
Version: 0.1.5
Summary: A python package for common biological data I/O
Home-page: https://github.com/aldenleung/biodata/
Author: Alden Leung
Author-email: alden.leung@gmail.com
Classifier: Programming Language :: Python :: 3.7
Classifier: Programming Language :: Python :: 3.8
Classifier: Programming Language :: Python :: 3.9
Classifier: Programming Language :: Python :: 3.10
Classifier: Programming Language :: Python :: 3.11
Classifier: License :: OSI Approved :: GNU General Public License v3 (GPLv3)
Requires-Dist: genomictools>=0.0.8
